django_editorial_staff-0.8.0.dist-info/METADATA
django_editorial_staff-0.8.0.dist-info/RECORD
django_editorial_staff-0.8.0.dist-info/WHEEL
django_editorial_staff-0.8.0.dist-info/top_level.txt
editorial_staff/__init__.py
editorial_staff/admin.py
editorial_staff/apps.py
editorial_staff/checks.py
editorial_staff/field_renderers.py
editorial_staff/fields.py
editorial_staff/forms.py
editorial_staff/mixins.py
editorial_staff/models.py
editorial_staff/signals.py
editorial_staff/tests.py
editorial_staff/urls.py
editorial_staff/utils.py
editorial_staff/validators.py
editorial_staff/views.py
editorial_staff/widgets.py
editorial_staff/api/__init__.py
editorial_staff/api/urls.py
editorial_staff/api/versions/__init__.py
editorial_staff/api/versions/v1/__init__.py
editorial_staff/api/versions/v1/urls.py
editorial_staff/api/versions/v1/views.py
editorial_staff/api/versions/v2/__init__.py
editorial_staff/api/versions/v2/mixins.py
editorial_staff/api/versions/v2/router.py
editorial_staff/api/versions/v2/serializers.py
editorial_staff/api/versions/v2/views.py
editorial_staff/data_providers/__init__.py
editorial_staff/data_providers/base.py
editorial_staff/data_providers/slack.py
editorial_staff/loaders/__init__.py
editorial_staff/loaders/slack.py
editorial_staff/management/__init__.py
editorial_staff/management/commands/__init__.py
editorial_staff/management/commands/createslackbylines.py
editorial_staff/migrations/0001_initial.py
editorial_staff/migrations/0002_staffer_active.py
editorial_staff/migrations/0003_auto_20170821_1239.py
editorial_staff/migrations/0004_auto_20170921_0032.py
editorial_staff/migrations/0005_staffer_created.py
editorial_staff/migrations/0006_staffer_full_name.py
editorial_staff/migrations/0007_populate_staffer_full_names.py
editorial_staff/migrations/__init__.py
editorial_staff/static/editorial_staff/css/alerts.css
editorial_staff/static/editorial_staff/css/main.css
editorial_staff/static/editorial_staff/css/main.css.map
editorial_staff/static/editorial_staff/css/snackbar.css
editorial_staff/static/editorial_staff/css/snackbar.css.map
editorial_staff/static/editorial_staff/css/styles.css
